aprheology/__init__.py
aprheology/gui.py
aprheology/relaxation.py
aprheology-0.3.2.dist-info/LICENSE
aprheology-0.3.2.dist-info/METADATA
aprheology-0.3.2.dist-info/WHEEL
aprheology-0.3.2.dist-info/top_level.txt
aprheology-0.3.2.dist-info/RECORD
