Metadata-Version: 2.1
Name: aprheology
Version: 0.3.2
Summary: Set of tools to easily analyse Anton Paar rheometer data
Home-page: UNKNOWN
Author: Kevin De Bruycker
Author-email: kevindebruycker@gmail.com
License: MIT License
Platform: UNKNOWN
Classifier: Programming Language :: Python :: 3
Classifier: Programming Language :: Python :: 3.7
Classifier: License :: OSI Approved :: MIT License
Classifier: Operating System :: OS Independent
Requires-Python: >=3.6
Requires-Dist: matplotlib
Requires-Dist: numpy
Requires-Dist: openpyxl
Requires-Dist: pandas
Requires-Dist: PySimpleGUI
Requires-Dist: scipy
Requires-Dist: statsmodels
